Workbook

Sheet README
A1: About this model
A3: Color legend:
A4: Blue text = hardcoded input
A5: Black text = formula
A6: Yellow fill = key assumption / output worth flagging (e.g. WACC, terminal growth)
A9: Model structure notes:
A10: Revenue is driven by geographic mix (US vs. International) and reimbursement/pricing dynamics, reflecting DexCom's actual disclosed segmentation. R&D is broken out separately from SG&A, (~13% of revenue) since it's a large enough expense to isolate rather than hide it inside a single opex line. Working capital includes real accounts receivable (DSO), since Dexcom sells largely through insurance channels rather than for cash.
A13: Tab order and what each is for:
A14: 1. Assumptions: every driver and input
A15: 2. Revenue Build: turns US/International growth + pricing assumptions into a $ revenue line
A16: 3. Opex & EBITDA: gross margin, R&D, and SG&A assumptions turn revenue into EBITDA/EBIT
A17: 4. Capex & D&A: capital spending (manufacturing capacity) and depreciation schedule
... A23: 10. Summary Dashboard: one-page output: implied share price, key assumptions

Sheet Assumptions
A1: DexCom, Inc. (NASDAQ: DXCM) — DCF Model
A2: Tab 1: Assumptions & Drivers
A3: $ in millions unless noted. Fiscal year ends Dec 31.
A5: Line item | B5: FY2023A | C5: FY2024A | D5: FY2025A | E5: FY2026E | F5: FY2027E | G5: FY2028E | H5: FY2029E | I5: FY2030E
A7: 1. Revenue Drivers — Geographic Mix & Growth
A8: US revenue growth (%) | B8: =('Revenue Build'!C7-'Revenue Build'!B7)/'Revenue Build'!B7 -> 0.22563025 | C8: =('Revenue Build'!D7-'Revenue Build'!C7)/'Revenue Build'!C7 -> 0.10075039 | D8: =('Revenue Build'!E7-'Revenue Build'!D7)/'Revenue Build'!D7 -> 0.1540245 | E8: 0.12 | F8: 0.12 | G8: 0.11 | H8: 0.1 | I8: 0.09
A9: International revenue growth (%) | B9: =('Revenue Build'!C8-'Revenue Build'!B8)/'Revenue Build'!B8 -> 0.29851524 | C9: =('Revenue Build'!D8-'Revenue Build'!C8)/'Revenue Build'!C8 -> 0.14663992 | D9: =('Revenue Build'!E8-'Revenue Build'!D8)/'Revenue Build'!D8 -> 0.16086424 | E9: 0.16 | F9: 0.16 | G9: 0.15 | H9: 0.13 | I9: 0.11
A10: US revenue (% of total) | B10: ='Revenue Build'!C7/'Revenue Build'!C$9 -> 0.72476051 | C10: ='Revenue Build'!D7/'Revenue Build'!D$9 -> 0.71653856 | D10: ='Revenue Build'!E7/'Revenue Build'!E$9 -> 0.71533677 | E10: ='Revenue Build'!F7/'Revenue Build'!F$9 -> 0.70813745 | F10: ='Revenue Build'!G7/'Revenue Build'!G$9 -> 0.70083222 | G10: ='Revenue Build'!H7/'Revenue Build'!H$9 -> 0.69335726 | H10: ='Revenue Build'!I7/'Revenue Build'!I$9 -> 0.68760681 | I10: ='Revenue Build'!J7/'Revenue Build'!J$9 -> 0.68368792
A11: International revenue (% of total) | B11: ='Revenue Build'!C8/'Revenue Build'!C$9 -> 0.27523949 | C11: ='Revenue Build'!D8/'Revenue Build'!D$9 -> 0.28346144 | D11: ='Revenue Build'!E8/'Revenue Build'!E$9 -> 0.28466323 | E11: ='Revenue Build'!F8/'Revenue Build'!F$9 -> 0.29186255 | F11: ='Revenue Build'!G8/'Revenue Build'!G$9 -> 0.29916778 | G11: ='Revenue Build'!H8/'Revenue Build'!H$9 -> 0.30664274 | H11: ='Revenue Build'!I8/'Revenue Build'!I$9 -> 0.31239319 | I11: ='Revenue Build'!J8/'Revenue Build'!J$9 -> 0.31631208
A13: 2. Margin Assumptions
A14: Gross margin (%) | B14: =('Opex & EBITDA'!B9)/('Opex & EBITDA'!B7) -> 0.63189134 | C14: =('Opex & EBITDA'!C9)/('Opex & EBITDA'!C7) -> 0.60456236 | D14: =('Opex & EBITDA'!D9)/('Opex & EBITDA'!D7) -> 0.60100815 | E14: 0.6 | F14: 0.6 | G14: 0.598 | H14: 0.598 | I14: 0.597
A15: R&D expense (% of revenue) | B15: ='Opex & EBITDA'!B10/'Opex & EBITDA'!B7 -> 0.13963504 | C15: ='Opex & EBITDA'!C10/'Opex & EBITDA'!C7 -> 0.13697 | D15: ='Opex & EBITDA'!D10/'Opex & EBITDA'!D7 -> 0.12850708 | E15: 0.125 | F15: 0.12 | G15: 0.115 | H15: 0.11 | I15: 0.105
A16: SG&A expense (% of revenue) | B16: ='Opex & EBITDA'!B11/'Opex & EBITDA'!B7 -> 0.32725064 | C16: ='Opex & EBITDA'!C11/'Opex & EBITDA'!C7 -> 0.31881974 | D16: ='Opex & EBITDA'!D11/'Opex & EBITDA'!D7 -> 0.27691978 | E16: 0.265 | F16: 0.255 | G16: 0.245 | H16: 0.235 | I16: 0.225
A18: 3. Capex & D&A
A19: Capex (% of revenue) | B19: ='Capex & DA'!B8/'Capex & DA'!B7 -> 0.065317616 | C19: ='Capex & DA'!C8/'Capex & DA'!C7 -> 0.08896603 | D19: ='Capex & DA'!D8/'Capex & DA'!D7 -> 0.077970828 | E19: 0.075 | F19: 0.073 | G19: 0.07 | H19: 0.068 | I19: 0.065
A20: D&A (% of revenue) | B20: ='Capex & DA'!B11/'Capex & DA'!B7 -> 0.051348591 | C20: ='Capex & DA'!C11/'Capex & DA'!C7 -> 0.053979668 | D20: ='Capex & DA'!D11/'Capex & DA'!D7 -> 0.054011154 | E20: 0.054 | F20: 0.055 | G20: 0.055 | H20: 0.056 | I20: 0.056
A22: 4. Working Capital
A23: Inventory days (DIO, based on COGS) | B23: ='Working Capital'!B9/'Working Capital'!B8*365 -> 153.18284 | C23: ='Working Capital'!C9/'Working Capital'!C8*365 -> 124.18422 | D23: ='Working Capital'!D9/'Working Capital'!D8*365 -> 123.44578 | E23: 122 | F23: 120 | G23: 118 | H23: 117 | I23: 116
A24: Accounts receivable days (DSO, based on revenue) | B24: ='Working Capital'!B10/'Working Capital'!B7*365 -> 98.134749 | C24: ='Working Capital'!C10/'Working Capital'!C7*365 -> 91.019216 | D24: ='Working Capital'!D10/'Working Capital'!D7*365 -> 95.211604 | E24: 94 | F24: 93 | G24: 92 | H24: 92 | I24: 91
A25: Accounts payable days (DPO, based on COGS) | B25: ='Working Capital'!B11/'Working Capital'!B8*365 -> 368.31221 | C25: ='Working Capital'!C11/'Working Capital'!C8*365 -> 362.77997 | D25: ='Working Capital'!D11/'Working Capital'!D8*365 -> 381.46336 | E25: 385 | F25: 388 | G25: 390 | H25: 390 | I25: 390
A27: 5. Tax Rate
A28: Effective tax rate (%) | B28: 0.2316 | C28: 0.1873 | D28: 0.2377 | E28: 0.24 | F28: 0.24 | G28: 0.24 | H28: 0.24 | I28: 0.24
A30: 6. WACC Inputs (single point-in-time estimate — put in column B only)
A31: Risk-free rate (10yr UST) | B31: 0.0468
A32: Equity risk premium | B32: 0.0445
A33: Levered beta | B33: 1.45
A34: Cost of equity (CAPM) — formula | B34: =B31+B33*B32 -> 0.111325
A35: Pre-tax cost of debt | B35: 0.0575
A36: Tax rate (for WACC) | B36: 0.24
A37: After-tax cost of debt — formula | B37: =B35*(1-B36) -> 0.0437
A38: Target debt / total capital | B38: 0.125
A39: Target equity / total capital — formula | B39: =1-B38 -> 0.875
A40: WACC — formula | B40: =B39*B34+B38*B37 -> 0.10287188
A42: 7. Terminal Value Assumptions
A43: Terminal (perpetuity) growth rate | B43: 0.025
A44: Exit EV/EBITDA multiple (cross-check) | B44: 16.5

Sheet Revenue Build
A1: DexCom, Inc. (NASDAQ: DXCM) — DCF Model
A2: Tab 2: Revenue Build
A3: $ in millions unless noted. Fiscal year ends Dec 31.
A5: Line item | B5: FY2022A | C5: FY2023A | D5: FY2024A | E5: FY2025A | F5: FY2026E | G5: FY2027E | H5: FY2028E | I5: FY2029E | J5: FY2030E
A7: US revenue | B7: 2142 | C7: 2625.3 | D7: 2889.8 | E7: 3334.9 | F7: =E7*(1+Assumptions!E8) -> 3735.088 | G7: =F7*(1+Assumptions!F8) -> 4183.2986 | H7: =G7*(1+Assumptions!G8) -> 4643.4614 | I7: =H7*(1+Assumptions!H8) -> 5107.8075 | J7: =I7*(1+Assumptions!I8) -> 5567.5102
A8: International revenue | B8: 767.8 | C8: 997 | D8: 1143.2 | E8: 1327.1 | F8: =E8*(1+Assumptions!E9) -> 1539.436 | G8: =F8*(1+Assumptions!F9) -> 1785.7458 | H8: =G8*(1+Assumptions!G9) -> 2053.6076 | I8: =H8*(1+Assumptions!H9) -> 2320.5766 | J8: =I8*(1+Assumptions!I9) -> 2575.84
A9: Total revenue | B9: 2909.8 | C9: 3622.3 | D9: 4033 | E9: 4662 | F9: =SUM(F7:F8) -> 5274.524 | G9: =SUM(G7:G8) -> 5969.0443 | H9: =SUM(H7:H8) -> 6697.069 | I9: =SUM(I7:I8) -> 7428.3842 | J9: =SUM(J7:J8) -> 8143.3503

Sheet Opex & EBITDA
A1: DexCom, Inc. (NASDAQ: DXCM) — DCF Model
A2: Tab 3: Opex, EBITDA & EBIT
A3: $ in millions unless noted. Fiscal year ends Dec 31.
A5: Line item | B5: FY2023A | C5: FY2024A | D5: FY2025A | E5: FY2026E | F5: FY2027E | G5: FY2028E | H5: FY2029E | I5: FY2030E
A7: Total revenue (link) | B7: ='Revenue Build'!C9 -> 3622.3 | C7: ='Revenue Build'!D9 -> 4033 | D7: ='Revenue Build'!E9 -> 4662 | E7: ='Revenue Build'!F9 -> 5274.524 | F7: ='Revenue Build'!G9 -> 5969.0443 | G7: ='Revenue Build'!H9 -> 6697.069 | H7: ='Revenue Build'!I9 -> 7428.3842 | I7: ='Revenue Build'!J9 -> 8143.3503
A8: Cost of sales | B8: 1333.4 | C8: 1594.8 | D8: 1860.1 | E8: =E7*(1-Assumptions!E14) -> 2109.8096 | F8: =F7*(1-Assumptions!F14) -> 2387.6177 | G8: =G7*(1-Assumptions!G14) -> 2692.2217 | H8: =H7*(1-Assumptions!H14) -> 2986.2104 | I8: =I7*(1-Assumptions!I14) -> 3281.7702
A9: Gross profit | B9: =B7-B8 -> 2288.9 | C9: =C7-C8 -> 2438.2 | D9: =D7-D8 -> 2801.9 | E9: =E7-E8 -> 3164.7144 | F9: =F7-F8 -> 3581.4266 | G9: =G7-G8 -> 4004.8473 | H9: =H7-H8 -> 4442.1737 | I9: =I7-I8 -> 4861.5801
A10: R&D expense | B10: 505.8 | C10: 552.4 | D10: 599.1 | E10: =E7*Assumptions!E15 -> 659.3155 | F10: =F7*Assumptions!F15 -> 716.28532 | G10: =G7*Assumptions!G15 -> 770.16294 | H10: =H7*Assumptions!H15 -> 817.12226 | I10: =I7*Assumptions!I15 -> 855.05178
A11: SG&A expense | B11: 1185.4 | C11: 1285.8 | D11: 1291 | E11: =E7*Assumptions!E16 -> 1397.7489 | F11: =F7*Assumptions!F16 -> 1522.1063 | G11: =G7*Assumptions!G16 -> 1640.7819 | H11: =H7*Assumptions!H16 -> 1745.6703 | I11: =I7*Assumptions!I16 -> 1832.2538
A12: EBIT | B12: =B9-B10-B11 -> 597.7 | C12: =C9-C10-C11 -> 600 | D12: =D9-D10-D11 -> 911.8 | E12: =E9-E10-E11 -> 1107.65 | F12: =F9-F10-F11 -> 1343.035 | G12: =G9-G10-G11 -> 1593.9024 | H12: =H9-H10-H11 -> 1879.3812 | I12: =I9-I10-I11 -> 2174.2745
A13: D&A (link from Capex & D&A tab) | B13: ='Capex & DA'!B11 -> 186 | C13: ='Capex & DA'!C11 -> 217.7 | D13: ='Capex & DA'!D11 -> 251.8 | E13: ='Capex & DA'!E11 -> 284.8243 | F13: ='Capex & DA'!F11 -> 328.29744 | G13: ='Capex & DA'!G11 -> 368.3388 | H13: ='Capex & DA'!H11 -> 415.98951 | I13: ='Capex & DA'!I11 -> 456.02761
A14: EBITDA | B14: =B12+B13 -> 783.7 | C14: =C12+C13 -> 817.7 | D14: =D12+D13 -> 1163.6 | E14: =E12+E13 -> 1392.4743 | F14: =F12+F13 -> 1671.3324 | G14: =G12+G13 -> 1962.2412 | H14: =H12+H13 -> 2295.3707 | I14: =I12+I13 -> 2630.3021

Sheet Capex & DA
A1: DexCom, Inc. (NASDAQ: DXCM) — DCF Model
A2: Tab 4: Capex & D&A Schedule
A3: $ in millions unless noted. Fiscal year ends Dec 31.
A5: Line item | B5: FY2023A | C5: FY2024A | D5: FY2025A | E5: FY2026E | F5: FY2027E | G5: FY2028E | H5: FY2029E | I5: FY2030E
A7: Total revenue (link) | B7: ='Revenue Build'!C9 -> 3622.3 | C7: ='Revenue Build'!D9 -> 4033 | D7: ='Revenue Build'!E9 -> 4662 | E7: ='Revenue Build'!F9 -> 5274.524 | F7: ='Revenue Build'!G9 -> 5969.0443 | G7: ='Revenue Build'!H9 -> 6697.069 | H7: ='Revenue Build'!I9 -> 7428.3842 | I7: ='Revenue Build'!J9 -> 8143.3503
A8: Capex | B8: 236.6 | C8: 358.8 | D8: 363.5 | E8: =E7*Assumptions!E19 -> 395.5893 | F8: =F7*Assumptions!F19 -> 435.74024 | G8: =G7*Assumptions!G19 -> 468.79483 | H8: =H7*Assumptions!H19 -> 505.13012 | I8: =I7*Assumptions!I19 -> 529.31777
A9: Beginning gross PP&E | B9: 1418.8 | C9: =B10 -> 1622.5 | D9: =C10 -> 2018.2 | E9: =D10 -> 2418.7 | F9: =E10 -> 2814.2893 | G9: =F10 -> 3250.0295 | H9: =G10 -> 3718.8244 | I9: =H10 -> 4223.9545
A10: Ending gross PP&E | B10: 1622.5 | C10: 2018.2 | D10: 2418.7 | E10: =E9+E8 -> 2814.2893 | F10: =F9+F8 -> 3250.0295 | G10: =G9+G8 -> 3718.8244 | H10: =H9+H8 -> 4223.9545 | I10: =I9+I8 -> 4753.2723
A11: D&A expense | B11: 186 | C11: 217.7 | D11: 251.8 | E11: =E7*Assumptions!E20 -> 284.8243 | F11: =F7*Assumptions!F20 -> 328.29744 | G11: =G7*Assumptions!G20 -> 368.3388 | H11: =H7*Assumptions!H20 -> 415.98951 | I11: =I7*Assumptions!I20 -> 456.02761
A12: Accumulated D&A | B12: 509.4 | C12: 678.3 | D12: 858.8 | E12: =D12+E11 -> 1143.6243 | F12: =E12+F11 -> 1471.9217 | G12: =F12+G11 -> 1840.2605 | H12: =G12+H11 -> 2256.25 | I12: =H12+I11 -> 2712.2777
A13: Net PP&E | B13: =B10-B12 -> 1113.1 | C13: =C10-C12 -> 1339.9 | D13: =D10-D12 -> 1559.9 | E13: =E10-E12 -> 1670.665 | F13: =F10-F12 -> 1778.1078 | G13: =G10-G12 -> 1878.5638 | H13: =H10-H12 -> 1967.7044 | I13: =I10-I12 -> 2040.9946

Sheet Working Capital
A1: DexCom, Inc. (NASDAQ: DXCM) — DCF Model
A2: Tab 5: Working Capital Schedule
A3: $ in millions unless noted. Fiscal year ends Dec 31.
A5: Line item | B5: FY2023A | C5: FY2024A | D5: FY2025A | E5: FY2026E | F5: FY2027E | G5: FY2028E | H5: FY2029E | I5: FY2030E
A7: Total revenue (link) | B7: ='Revenue Build'!C9 -> 3622.3 | C7: ='Revenue Build'!D9 -> 4033 | D7: ='Revenue Build'!E9 -> 4662 | E7: ='Revenue Build'!F9 -> 5274.524 | F7: ='Revenue Build'!G9 -> 5969.0443 | G7: ='Revenue Build'!H9 -> 6697.069 | H7: ='Revenue Build'!I9 -> 7428.3842 | I7: ='Revenue Build'!J9 -> 8143.3503
A8: Cost of sales (link) | B8: ='Opex & EBITDA'!B8 -> 1333.4 | C8: ='Opex & EBITDA'!C8 -> 1594.8 | D8: ='Opex & EBITDA'!D8 -> 1860.1 | E8: ='Opex & EBITDA'!E8 -> 2109.8096 | F8: ='Opex & EBITDA'!F8 -> 2387.6177 | G8: ='Opex & EBITDA'!G8 -> 2692.2217 | H8: ='Opex & EBITDA'!H8 -> 2986.2104 | I8: ='Opex & EBITDA'!I8 -> 3281.7702
A9: Inventory | B9: 559.6 | C9: 542.6 | D9: 629.1 | E9: =Assumptions!E23/365*'Working Capital'!E8 -> 705.19663 | F9: =Assumptions!F23/365*'Working Capital'!F8 -> 784.97021 | G9: =Assumptions!G23/365*'Working Capital'!G8 -> 870.3621 | H9: =Assumptions!H23/365*'Working Capital'!H8 -> 957.22362 | I9: =Assumptions!I23/365*'Working Capital'!I8 -> 1042.9735
A10: Accounts receivable | B10: 973.9 | C10: 1005.7 | D10: 1216.1 | E10: =Assumptions!E24/365*E7 -> 1358.3706 | F10: =Assumptions!F24/365*F7 -> 1520.8798 | G10: =Assumptions!G24/365*G7 -> 1688.0284 | H10: =Assumptions!H24/365*H7 -> 1872.3598 | I10: =Assumptions!I24/365*I7 -> 2030.2599
A11: Accounts payable & accrued liabilities | B11: 1345.5 | C11: 1585.1 | D11: 1944 | E11: =Assumptions!E25/365*E8 -> 2225.4156 | F11: =Assumptions!F25/365*F8 -> 2538.0704 | G11: =Assumptions!G25/365*G8 -> 2876.6205 | H11: =Assumptions!H25/365*H8 -> 3190.7454 | I11: =Assumptions!I25/365*I8 -> 3506.5489
A12: Net working capital | B12: =B9+B10-B11 -> 188 | C12: =C9+C10-C11 -> -36.8 | D12: =D9+D10-D11 -> -98.8 | E12: =E9+E10-E11 -> -161.84841 | F12: =F9+F10-F11 -> -232.22035 | G12: =G9+G10-G11 -> -318.23004 | H12: =H9+H10-H11 -> -361.16193 | I12: =I9+I10-I11 -> -433.31548
A13: Change in NWC (cash flow impact) | B13: 69.8 | C13: =C12-B12 -> -224.8 | D13: =D12-C12 -> -62 | E13: =E12-D12 -> -63.048408 | F13: =F12-E12 -> -70.371947 | G13: =G12-F12 -> -86.009687 | H13: =H12-G12 -> -42.931891 | I13: =I12-H12 -> -72.153544

Sheet Unlevered FCF
A1: DexCom, Inc. (NASDAQ: DXCM) — DCF Model
A2: Tab 6: Unlevered Free Cash Flow
A3: $ in millions unless noted. Fiscal year ends Dec 31.
A5: Line item | B5: FY2023A | C5: FY2024A | D5: FY2025A | E5: FY2026E | F5: FY2027E | G5: FY2028E | H5: FY2029E | I5: FY2030E
A7: EBIT (link) | B7: ='Opex & EBITDA'!B12 -> 597.7 | C7: ='Opex & EBITDA'!C12 -> 600 | D7: ='Opex & EBITDA'!D12 -> 911.8 | E7: ='Opex & EBITDA'!E12 -> 1107.65 | F7: ='Opex & EBITDA'!F12 -> 1343.035 | G7: ='Opex & EBITDA'!G12 -> 1593.9024 | H7: ='Opex & EBITDA'!H12 -> 1879.3812 | I7: ='Opex & EBITDA'!I12 -> 2174.2745
A8: Tax rate (link) | B8: =Assumptions!B28 -> 0.2316 | C8: =Assumptions!C28 -> 0.1873 | D8: =Assumptions!D28 -> 0.2377 | E8: =Assumptions!E28 -> 0.24 | F8: =Assumptions!F28 -> 0.24 | G8: =Assumptions!G28 -> 0.24 | H8: =Assumptions!H28 -> 0.24 | I8: =Assumptions!I28 -> 0.24
A9: NOPAT (EBIT x (1-tax)) | B9: =B7*(1-B8) -> 459.27268 | C9: =C7*(1-C8) -> 487.62 | D9: =D7*(1-D8) -> 695.06514 | E9: =E7*(1-E8) -> 841.81403 | F9: =F7*(1-F8) -> 1020.7066 | G9: =G7*(1-G8) -> 1211.3658 | H9: =H7*(1-H8) -> 1428.3297 | I9: =I7*(1-I8) -> 1652.4486
A10: Plus: D&A | B10: ='Capex & DA'!B11 -> 186 | C10: ='Capex & DA'!C11 -> 217.7 | D10: ='Capex & DA'!D11 -> 251.8 | E10: ='Capex & DA'!E11 -> 284.8243 | F10: ='Capex & DA'!F11 -> 328.29744 | G10: ='Capex & DA'!G11 -> 368.3388 | H10: ='Capex & DA'!H11 -> 415.98951 | I10: ='Capex & DA'!I11 -> 456.02761
A11: Less: Capex | B11: ='Capex & DA'!B8 -> 236.6 | C11: ='Capex & DA'!C8 -> 358.8 | D11: ='Capex & DA'!D8 -> 363.5 | E11: ='Capex & DA'!E8 -> 395.5893 | F11: ='Capex & DA'!F8 -> 435.74024 | G11: ='Capex & DA'!G8 -> 468.79483 | H11: ='Capex & DA'!H8 -> 505.13012 | I11: ='Capex & DA'!I8 -> 529.31777
A12: Less: Increase in NWC | B12: ='Working Capital'!B13 -> 69.8 | C12: ='Working Capital'!C13 -> -224.8 | D12: ='Working Capital'!D13 -> -62 | E12: ='Working Capital'!E13 -> -63.048408 | F12: ='Working Capital'!F13 -> -70.371947 | G12: ='Working Capital'!G13 -> -86.009687 | H12: ='Working Capital'!H13 -> -42.931891 | I12: ='Working Capital'!I13 -> -72.153544
A13: Unlevered Free Cash Flow | B13: =B9+B10-B11-B12 -> 338.87268 | C13: =C9+C10-C11-C12 -> 571.32 | D13: =D9+D10-D11-D12 -> 645.36514 | E13: =E9+E10-E11-E12 -> 794.09743 | F13: =F9+F10-F11-F12 -> 983.63573 | G13: =G9+G10-G11-G12 -> 1196.9195 | H13: =H9+H10-H11-H12 -> 1382.121 | I13: =I9+I10-I11-I12 -> 1651.312

Sheet WACC
A1: DexCom, Inc. (NASDAQ: DXCM) — DCF Model
A2: Tab 7: WACC Build
A3: $ in millions unless noted. Fiscal year ends Dec 31.
A5: Line item
A7: Cost of equity (CAPM) | B7: =Assumptions!B34 -> 0.111325
A8: After-tax cost of debt | B8: =Assumptions!B37 -> 0.0437
A9: Equity weight | B9: =Assumptions!B39 -> 0.875
A10: Debt weight | B10: =Assumptions!B38 -> 0.125
A11: WACC | B11: =Assumptions!B40 -> 0.10287188

Sheet DCF & Valuation
A1: DexCom, Inc. (NASDAQ: DXCM) — DCF Model
A2: Tab 8: DCF & Valuation
A3: $ in millions unless noted. Fiscal year ends Dec 31.
A5: Line item | B5: FY2026E | C5: FY2027E | D5: FY2028E | E5: FY2029E | F5: FY2030E
A7: Unlevered FCF (link) | B7: ='Unlevered FCF'!E13 -> 794.09743 | C7: ='Unlevered FCF'!F13 -> 983.63573 | D7: ='Unlevered FCF'!G13 -> 1196.9195 | E7: ='Unlevered FCF'!H13 -> 1382.121 | F7: ='Unlevered FCF'!I13 -> 1651.312
A8: Discount period | B8: 1 | C8: 2 | D8: 3 | E8: 4 | F8: 5
A9: Discount factor (1/(1+WACC)^n) | B9: =1/(1+WACC!$B$11)^'DCF & Valuation'!B8 -> 0.90672364 | C9: =1/(1+WACC!$B$11)^'DCF & Valuation'!C8 -> 0.82214776 | D9: =1/(1+WACC!$B$11)^'DCF & Valuation'!D8 -> 0.74546081 | E9: =1/(1+WACC!$B$11)^'DCF & Valuation'!E8 -> 0.67592694 | F9: =1/(1+WACC!$B$11)^'DCF & Valuation'!F8 -> 0.61287893
A10: PV of FCF | B10: =B7*B9 -> 720.02692 | C10: =C7*C9 -> 808.69391 | D10: =D7*D9 -> 892.25657 | E10: =E7*E9 -> 934.2128 | F10: =F7*F9 -> 1012.0543
A11: Sum of PV of explicit FCF | B11: =SUM(B10:F10) -> 4367.2445
A12: Terminal value (Gordon Growth) | F12: =(F7*(1+Assumptions!B43))/(WACC!$B$11-Assumptions!B43) -> 21735.637
A13: PV of terminal value | F13: =F12*F9 -> 13321.314
A15: Valuation Summary
A16: Enterprise value | B16: =B11+F13 -> 17688.559
A17: Less: net debt | B17: -757.8
A18: Equity value | B18: =B16-B17 -> 18446.359
A19: Diluted shares outstanding | B19: 405.5
A20: Implied share price | B20: =B18/B19 -> 45.490404

Sheet Sensitivity
A1: DexCom, Inc. (NASDAQ: DXCM) — DCF Model
A2: Tab 9: Sensitivity Analysis
A3: $ in millions unless noted. Fiscal year ends Dec 31.
B8: Sensitivity: Implied Share Price - WACC vs. Terminal Growth
E11: Terminal Growth
B12: WACC | C12: 0.015 | D12: 0.02 | E12: 0.025 | F12: 0.03 | G12: 0.035
B13: 0.09 | C13: =(NPV($B13,'Unlevered FCF'!$E$13:$I$13)+('Unlevered FCF'!$I$13*(1+C$12))/($B13-C$12)/(1+$B13)^5-'DCF & Valuation'!$B$17)/'DCF & Valuation'!$B$19 -> 48.866473 | D13: =(NPV($B13,'Unlevered FCF'!$E$13:$I$13)+('Unlevered FCF'!$I$13*(1+D$12))/($B13-D$12)/(1+$B13)^5-'DCF & Valuation'!$B$17)/'DCF & Valuation'!$B$19 -> 51.614006 | E13: =(NPV($B13,'Unlevered FCF'!$E$13:$I$13)+('Unlevered FCF'!$I$13*(1+E$12))/($B13-E$12)/(1+$B13)^5-'DCF & Valuation'!$B$17)/'DCF & Valuation'!$B$19 -> 54.784237 | F13: =(NPV($B13,'Unlevered FCF'!$E$13:$I$13)+('Unlevered FCF'!$I$13*(1+F$12))/($B13-F$12)/(1+$B13)^5-'DCF & Valuation'!$B$17)/'DCF & Valuation'!$B$19 -> 58.48284 | G13: =(NPV($B13,'Unlevered FCF'!$E$13:$I$13)+('Unlevered FCF'!$I$13*(1+G$12))/($B13-G$12)/(1+$B13)^5-'DCF & Valuation'!$B$17)/'DCF & Valuation'!$B$19 -> 62.853916
B14: 0.095 | C14: =(NPV($B14,'Unlevered FCF'!$E$13:$I$13)+('Unlevered FCF'!$I$13*(1+C$12))/($B14-C$12)/(1+$B14)^5-'DCF & Valuation'!$B$17)/'DCF & Valuation'!$B$19 -> 45.706535 | D14: =(NPV($B14,'Unlevered FCF'!$E$13:$I$13)+('Unlevered FCF'!$I$13*(1+D$12))/($B14-D$12)/(1+$B14)^5-'DCF & Valuation'!$B$17)/'DCF & Valuation'!$B$19 -> 48.067016 | E14: =(NPV($B14,'Unlevered FCF'!$E$13:$I$13)+('Unlevered FCF'!$I$13*(1+E$12))/($B14-E$12)/(1+$B14)^5-'DCF & Valuation'!$B$17)/'DCF & Valuation'!$B$19 -> 50.764709 | F14: =(NPV($B14,'Unlevered FCF'!$E$13:$I$13)+('Unlevered FCF'!$I$13*(1+F$12))/($B14-F$12)/(1+$B14)^5-'DCF & Valuation'!$B$17)/'DCF & Valuation'!$B$19 -> 53.877431 | G14: =(NPV($B14,'Unlevered FCF'!$E$13:$I$13)+('Unlevered FCF'!$I$13*(1+G$12))/($B14-G$12)/(1+$B14)^5-'DCF & Valuation'!$B$17)/'DCF & Valuation'!$B$19 -> 57.508941
B15: 0.1 | C15: =(NPV($B15,'Unlevered FCF'!$E$13:$I$13)+('Unlevered FCF'!$I$13*(1+C$12))/($B15-C$12)/(1+$B15)^5-'DCF & Valuation'!$B$17)/'DCF & Valuation'!$B$19 -> 42.922167 | D15: =(NPV($B15,'Unlevered FCF'!$E$13:$I$13)+('Unlevered FCF'!$I$13*(1+D$12))/($B15-D$12)/(1+$B15)^5-'DCF & Valuation'!$B$17)/'DCF & Valuation'!$B$19 -> 44.967333 | E15: =(NPV($B15,'Unlevered FCF'!$E$13:$I$13)+('Unlevered FCF'!$I$13*(1+E$12))/($B15-E$12)/(1+$B15)^5-'DCF & Valuation'!$B$17)/'DCF & Valuation'!$B$19 -> 47.285188 | F15: =(NPV($B15,'Unlevered FCF'!$E$13:$I$13)+('Unlevered FCF'!$I$13*(1+F$12))/($B15-F$12)/(1+$B15)^5-'DCF & Valuation'!$B$17)/'DCF & Valuation'!$B$19 -> 49.934166 | G15: =(NPV($B15,'Unlevered FCF'!$E$13:$I$13)+('Unlevered FCF'!$I$13*(1+G$12))/($B15-G$12)/(1+$B15)^5-'DCF & Valuation'!$B$17)/'DCF & Valuation'!$B$19 -> 52.990678
B16: 0.1029 | C16: =(NPV($B16,'Unlevered FCF'!$E$13:$I$13)+('Unlevered FCF'!$I$13*(1+C$12))/($B16-C$12)/(1+$B16)^5-'DCF & Valuation'!$B$17)/'DCF & Valuation'!$B$19 -> 41.45403 | D16: =(NPV($B16,'Unlevered FCF'!$E$13:$I$13)+('Unlevered FCF'!$I$13*(1+D$12))/($B16-D$12)/(1+$B16)^5-'DCF & Valuation'!$B$17)/'DCF & Valuation'!$B$19 -> 43.342545 | E16: =(NPV($B16,'Unlevered FCF'!$E$13:$I$13)+('Unlevered FCF'!$I$13*(1+E$12))/($B16-E$12)/(1+$B16)^5-'DCF & Valuation'!$B$17)/'DCF & Valuation'!$B$19 -> 45.473487 | F16: =(NPV($B16,'Unlevered FCF'!$E$13:$I$13)+('Unlevered FCF'!$I$13*(1+F$12))/($B16-F$12)/(1+$B16)^5-'DCF & Valuation'!$B$17)/'DCF & Valuation'!$B$19 -> 47.89674 | G16: =(NPV($B16,'Unlevered FCF'!$E$13:$I$13)+('Unlevered FCF'!$I$13*(1+G$12))/($B16-G$12)/(1+$B16)^5-'DCF & Valuation'!$B$17)/'DCF & Valuation'!$B$19 -> 50.676879
B17: 0.105 | C17: =(NPV($B17,'Unlevered FCF'!$E$13:$I$13)+('Unlevered FCF'!$I$13*(1+C$12))/($B17-C$12)/(1+$B17)^5-'DCF & Valuation'!$B$17)/'DCF & Valuation'!$B$19 -> 40.450689 | D17: =(NPV($B17,'Unlevered FCF'!$E$13:$I$13)+('Unlevered FCF'!$I$13*(1+D$12))/($B17-D$12)/(1+$B17)^5-'DCF & Valuation'!$B$17)/'DCF & Valuation'!$B$19 -> 42.235933 | E17: =(NPV($B17,'Unlevered FCF'!$E$13:$I$13)+('Unlevered FCF'!$I$13*(1+E$12))/($B17-E$12)/(1+$B17)^5-'DCF & Valuation'!$B$17)/'DCF & Valuation'!$B$19 -> 44.244334 | F17: =(NPV($B17,'Unlevered FCF'!$E$13:$I$13)+('Unlevered FCF'!$I$13*(1+F$12))/($B17-F$12)/(1+$B17)^5-'DCF & Valuation'!$B$17)/'DCF & Valuation'!$B$19 -> 46.520521 | G17: =(NPV($B17,'Unlevered FCF'!$E$13:$I$13)+('Unlevered FCF'!$I$13*(1+G$12))/($B17-G$12)/(1+$B17)^5-'DCF & Valuation'!$B$17)/'DCF & Valuation'!$B$19 -> 49.121877
B18: 0.11 | C18: =(NPV($B18,'Unlevered FCF'!$E$13:$I$13)+('Unlevered FCF'!$I$13*(1+C$12))/($B18-C$12)/(1+$B18)^5-'DCF & Valuation'!$B$17)/'DCF & Valuation'!$B$19 -> 38.242618 | D18: =(NPV($B18,'Unlevered FCF'!$E$13:$I$13)+('Unlevered FCF'!$I$13*(1+D$12))/($B18-D$12)/(1+$B18)^5-'DCF & Valuation'!$B$17)/'DCF & Valuation'!$B$19 -> 39.811355 | E18: =(NPV($B18,'Unlevered FCF'!$E$13:$I$13)+('Unlevered FCF'!$I$13*(1+E$12))/($B18-E$12)/(1+$B18)^5-'DCF & Valuation'!$B$17)/'DCF & Valuation'!$B$19 -> 41.56465 | F18: =(NPV($B18,'Unlevered FCF'!$E$13:$I$13)+('Unlevered FCF'!$I$13*(1+F$12))/($B18-F$12)/(1+$B18)^5-'DCF & Valuation'!$B$17)/'DCF & Valuation'!$B$19 -> 43.537107 | G18: =(NPV($B18,'Unlevered FCF'!$E$13:$I$13)+('Unlevered FCF'!$I$13*(1+G$12))/($B18-G$12)/(1+$B18)^5-'DCF & Valuation'!$B$17)/'DCF & Valuation'!$B$19 -> 45.772558
B19: 0.115 | C19: =(NPV($B19,'Unlevered FCF'!$E$13:$I$13)+('Unlevered FCF'!$I$13*(1+C$12))/($B19-C$12)/(1+$B19)^5-'DCF & Valuation'!$B$17)/'DCF & Valuation'!$B$19 -> 36.258371 | D19: =(NPV($B19,'Unlevered FCF'!$E$13:$I$13)+('Unlevered FCF'!$I$13*(1+D$12))/($B19-D$12)/(1+$B19)^5-'DCF & Valuation'!$B$17)/'DCF & Valuation'!$B$19 -> 37.645079 | E19: =(NPV($B19,'Unlevered FCF'!$E$13:$I$13)+('Unlevered FCF'!$I$13*(1+E$12))/($B19-E$12)/(1+$B19)^5-'DCF & Valuation'!$B$17)/'DCF & Valuation'!$B$19 -> 39.185866 | F19: =(NPV($B19,'Unlevered FCF'!$E$13:$I$13)+('Unlevered FCF'!$I$13*(1+F$12))/($B19-F$12)/(1+$B19)^5-'DCF & Valuation'!$B$17)/'DCF & Valuation'!$B$19 -> 40.907923 | G19: =(NPV($B19,'Unlevered FCF'!$E$13:$I$13)+('Unlevered FCF'!$I$13*(1+G$12))/($B19-G$12)/(1+$B19)^5-'DCF & Valuation'!$B$17)/'DCF & Valuation'!$B$19 -> 42.845236
B20: 0.12 | C20: =(NPV($B20,'Unlevered FCF'!$E$13:$I$13)+('Unlevered FCF'!$I$13*(1+C$12))/($B20-C$12)/(1+$B20)^5-'DCF & Valuation'!$B$17)/'DCF & Valuation'!$B$19 -> 34.465904 | D20: =(NPV($B20,'Unlevered FCF'!$E$13:$I$13)+('Unlevered FCF'!$I$13*(1+D$12))/($B20-D$12)/(1+$B20)^5-'DCF & Valuation'!$B$17)/'DCF & Valuation'!$B$19 -> 35.698291 | E20: =(NPV($B20,'Unlevered FCF'!$E$13:$I$13)+('Unlevered FCF'!$I$13*(1+E$12))/($B20-E$12)/(1+$B20)^5-'DCF & Valuation'!$B$17)/'DCF & Valuation'!$B$19 -> 37.060402 | F20: =(NPV($B20,'Unlevered FCF'!$E$13:$I$13)+('Unlevered FCF'!$I$13*(1+F$12))/($B20-F$12)/(1+$B20)^5-'DCF & Valuation'!$B$17)/'DCF & Valuation'!$B$19 -> 38.573859 | G20: =(NPV($B20,'Unlevered FCF'!$E$13:$I$13)+('Unlevered FCF'!$I$13*(1+G$12))/($B20-G$12)/(1+$B20)^5-'DCF & Valuation'!$B$17)/'DCF & Valuation'!$B$19 -> 40.26537
B22: Base case: WACC 10.29%, Terminal growth 2.5% ---> Implied share price of $45.47 (vs. current market price ~$86-89)
B24: Table Legend: Green = lower implied value, Red = higher implied value
B31: Sensitivity: Implied Share Price - Revenue Growth vs. Exit Multiple
E34: Exit Multiple
B35: Revenue Growth | C35: 13 | D35: 14.5 | E35: 16 | F35: 16.5 | G35: 18
B36: -0.2 | C36: =('DCF & Valuation'!$B$11+('Opex & EBITDA'!$I$14*(1+$B36)*C$35)/(1+WACC!$B$11)^5-'DCF & Valuation'!$B$17)/'DCF & Valuation'!$B$19 -> 53.98381 | D36: =('DCF & Valuation'!$B$11+('Opex & EBITDA'!$I$14*(1+$B36)*D$35)/(1+WACC!$B$11)^5-'DCF & Valuation'!$B$17)/'DCF & Valuation'!$B$19 -> 58.754385 | E36: =('DCF & Valuation'!$B$11+('Opex & EBITDA'!$I$14*(1+$B36)*E$35)/(1+WACC!$B$11)^5-'DCF & Valuation'!$B$17)/'DCF & Valuation'!$B$19 -> 63.52496 | F36: =('DCF & Valuation'!$B$11+('Opex & EBITDA'!$I$14*(1+$B36)*F$35)/(1+WACC!$B$11)^5-'DCF & Valuation'!$B$17)/'DCF & Valuation'!$B$19 -> 65.115151 | G36: =('DCF & Valuation'!$B$11+('Opex & EBITDA'!$I$14*(1+$B36)*G$35)/(1+WACC!$B$11)^5-'DCF & Valuation'!$B$17)/'DCF & Valuation'!$B$19 -> 69.885726
B37: -0.1 | C37: =('DCF & Valuation'!$B$11+('Opex & EBITDA'!$I$14*(1+$B37)*C$35)/(1+WACC!$B$11)^5-'DCF & Valuation'!$B$17)/'DCF & Valuation'!$B$19 -> 59.151933 | D37: =('DCF & Valuation'!$B$11+('Opex & EBITDA'!$I$14*(1+$B37)*D$35)/(1+WACC!$B$11)^5-'DCF & Valuation'!$B$17)/'DCF & Valuation'!$B$19 -> 64.518829 | E37: =('DCF & Valuation'!$B$11+('Opex & EBITDA'!$I$14*(1+$B37)*E$35)/(1+WACC!$B$11)^5-'DCF & Valuation'!$B$17)/'DCF & Valuation'!$B$19 -> 69.885726 | F37: =('DCF & Valuation'!$B$11+('Opex & EBITDA'!$I$14*(1+$B37)*F$35)/(1+WACC!$B$11)^5-'DCF & Valuation'!$B$17)/'DCF & Valuation'!$B$19 -> 71.674692 | G37: =('DCF & Valuation'!$B$11+('Opex & EBITDA'!$I$14*(1+$B37)*G$35)/(1+WACC!$B$11)^5-'DCF & Valuation'!$B$17)/'DCF & Valuation'!$B$19 -> 77.041588
B38: 0 | C38: =('DCF & Valuation'!$B$11+('Opex & EBITDA'!$I$14*(1+$B38)*C$35)/(1+WACC!$B$11)^5-'DCF & Valuation'!$B$17)/'DCF & Valuation'!$B$19 -> 64.320055 | D38: =('DCF & Valuation'!$B$11+('Opex & EBITDA'!$I$14*(1+$B38)*D$35)/(1+WACC!$B$11)^5-'DCF & Valuation'!$B$17)/'DCF & Valuation'!$B$19 -> 70.283274 | E38: =('DCF & Valuation'!$B$11+('Opex & EBITDA'!$I$14*(1+$B38)*E$35)/(1+WACC!$B$11)^5-'DCF & Valuation'!$B$17)/'DCF & Valuation'!$B$19 -> 76.246493 | F38: =('DCF & Valuation'!$B$11+('Opex & EBITDA'!$I$14*(1+$B38)*F$35)/(1+WACC!$B$11)^5-'DCF & Valuation'!$B$17)/'DCF & Valuation'!$B$19 -> 78.234232 | G38: =('DCF & Valuation'!$B$11+('Opex & EBITDA'!$I$14*(1+$B38)*G$35)/(1+WACC!$B$11)^5-'DCF & Valuation'!$B$17)/'DCF & Valuation'!$B$19 -> 84.197451
B39: 0.1 | C39: =('DCF & Valuation'!$B$11+('Opex & EBITDA'!$I$14*(1+$B39)*C$35)/(1+WACC!$B$11)^5-'DCF & Valuation'!$B$17)/'DCF & Valuation'!$B$19 -> 69.488178 | D39: =('DCF & Valuation'!$B$11+('Opex & EBITDA'!$I$14*(1+$B39)*D$35)/(1+WACC!$B$11)^5-'DCF & Valuation'!$B$17)/'DCF & Valuation'!$B$19 -> 76.047719 | E39: =('DCF & Valuation'!$B$11+('Opex & EBITDA'!$I$14*(1+$B39)*E$35)/(1+WACC!$B$11)^5-'DCF & Valuation'!$B$17)/'DCF & Valuation'!$B$19 -> 82.607259 | F39: =('DCF & Valuation'!$B$11+('Opex & EBITDA'!$I$14*(1+$B39)*F$35)/(1+WACC!$B$11)^5-'DCF & Valuation'!$B$17)/'DCF & Valuation'!$B$19 -> 84.793773 | G39: =('DCF & Valuation'!$B$11+('Opex & EBITDA'!$I$14*(1+$B39)*G$35)/(1+WACC!$B$11)^5-'DCF & Valuation'!$B$17)/'DCF & Valuation'!$B$19 -> 91.353313
B40: 0.2 | C40: =('DCF & Valuation'!$B$11+('Opex & EBITDA'!$I$14*(1+$B40)*C$35)/(1+WACC!$B$11)^5-'DCF & Valuation'!$B$17)/'DCF & Valuation'!$B$19 -> 74.656301 | D40: =('DCF & Valuation'!$B$11+('Opex & EBITDA'!$I$14*(1+$B40)*D$35)/(1+WACC!$B$11)^5-'DCF & Valuation'!$B$17)/'DCF & Valuation'!$B$19 -> 81.812163 | E40: =('DCF & Valuation'!$B$11+('Opex & EBITDA'!$I$14*(1+$B40)*E$35)/(1+WACC!$B$11)^5-'DCF & Valuation'!$B$17)/'DCF & Valuation'!$B$19 -> 88.968026 | F40: =('DCF & Valuation'!$B$11+('Opex & EBITDA'!$I$14*(1+$B40)*F$35)/(1+WACC!$B$11)^5-'DCF & Valuation'!$B$17)/'DCF & Valuation'!$B$19 -> 91.353313 | G40: =('DCF & Valuation'!$B$11+('Opex & EBITDA'!$I$14*(1+$B40)*G$35)/(1+WACC!$B$11)^5-'DCF & Valuation'!$B$17)/'DCF & Valuation'!$B$19 -> 98.509175
B42: Base case: 0% EBITDA adjustment, 16.5x exit multiple ---> Implied share price of $78.2(vs. Gordon Growth base case of $45.47)
B44: Gordon Growth assumes a lower implied exit multiple (~8x) than Dexcom's current trading multiple (16.5x), suggesting the perpetuity method may understate terminal value relative to market-based pricing.
B46: Table Legend: Green = lower implied value, Red = higher implied value

Sheet Summary Dashboard
A1: DexCom, Inc. (NASDAQ: DXCM) — DCF Model
A2: Tab 10: Summary Dashboard
A3: $ in millions unless noted. Fiscal year ends Dec 31.
A5: Key Assumptions Recap
A6: WACC | B6: =Assumptions!B40 -> 0.10287188
A7: Terminal growth rate | B7: =Assumptions!B43 -> 0.025
A8: FY2026E US revenue growth | B8: =Assumptions!E8 -> 0.12
A9: FY2026E International revenue growth | B9: =Assumptions!E9 -> 0.16
A10: FY2030E EBITDA margin | B10: ='Opex & EBITDA'!I14/'Opex & EBITDA'!I7 -> 0.323
A11: Implied share price (DCF) | B11: ='DCF & Valuation'!B20 -> 45.490404
A12: Implied upside/downside | B12: =(B11-B13)/B13 -> -0.49314313
A13: Current market share price | B13: 89.75
A14: Sensitivity table snapshot | B14: See Sensitivity tab for full WACC/Growth and Revenue/Multiple grids
A18: Key Judgment Calls
A19: • Reimbursement risk: Dexcom's own 10-K flags Medicare competitive bidding changes starting 2028 expected to lower CGM reimbursement. That's a company-acknowledged headwind on US growth specifically.
A20: • Terminal value cross-check: Gordon Growth implies a terminal EV/EBITDA multiple of ~8x, well below Dexcom's current trading multiple(~16.5x). This model's base case is more conservative than current market pricing - a deliberate choice to avoid reverse-engineering assumptions to match the market, though it means the DCF output($45.47) sits meaningfully below both the current share price(~86-89) and other published DCF estimates.
A21: • Beta assumption: Used a beta of ~1.45, consistent with most data providers (Google Finance, StockAnalysis.com), despite one outlier source (TradingView) showing 0.75. Chose the consensus estimate over the low outlier for a more defensible WACC.
A22: • Cost of debt: Used a market-based proxy (risk-free rate + credit spread, ~5.75%) rather than Dexcom's disclosed convertible note effective rates(0.5-0.7%), since those reflect embedded equity-conversion value rather than the cost of straight debt.
A23: • Working capital data limitation: Dexcom discloses "Accounts payable and accrued liabilities" as a single combined balance, not pure trade payables.
